filterlesscook/__init__.py
filterlesscook/filterlesscook.py
FilterlessCook-0.1.7.dist-info/METADATA
FilterlessCook-0.1.7.dist-info/WHEEL
FilterlessCook-0.1.7.dist-info/entry_points.txt
FilterlessCook-0.1.7.dist-info/top_level.txt
FilterlessCook-0.1.7.dist-info/RECORD
