Metadata-Version: 2.1
Name: FilterlessCook
Version: 0.1.7
Summary: Generate LaTeX formatted food recipes using the ollama library.
Author-email: Bissbert <dev@bissbert.ch>
License: MIT
Project-URL: Homepage, http://github.com/Bissbert/filterlesscook
Keywords: recipe generator,latex,unfiltered,filterless
Classifier: Development Status :: 3 - Alpha
Classifier: Intended Audience :: Developers
Classifier: License :: OSI Approved :: MIT License
Classifier: Programming Language :: Python :: 3
Classifier: Programming Language :: Python :: 3.6
Classifier: Programming Language :: Python :: 3.7
Requires-Dist: ollama
